./.gitignore
./PKG-INFO
./README.md
./pyproject.toml
./vision_agents/plugins/getstream/__init__.py
./vision_agents/plugins/getstream/stream_conversation.py
./vision_agents/plugins/getstream/stream_edge_transport.py
vision_agents/plugins/getstream/__init__.py
vision_agents/plugins/getstream/stream_conversation.py
vision_agents/plugins/getstream/stream_edge_transport.py
vision_agents_plugins_getstream-0.2.10.dist-info/METADATA
vision_agents_plugins_getstream-0.2.10.dist-info/WHEEL
vision_agents_plugins_getstream-0.2.10.dist-info/RECORD
