Metadata-Version: 2.4
Name: vision-agents-plugins-getstream
Version: 0.2.10
Summary: GetStream video/voice integration for Vision Agents
Project-URL: Documentation, https://visionagents.ai/
Project-URL: Website, https://visionagents.ai/
Project-URL: Source, https://github.com/GetStream/Vision-Agents
License-Expression: MIT
Keywords: AI,agents,getstream,realtime,streaming,video,voice agents
Requires-Python: >=3.10
Requires-Dist: getstream[telemetry,webrtc]>=2.5.21
Requires-Dist: vision-agents
